CHANGELOG.md
LICENSE
MANIFEST.in
README.md
setup.cfg
setup.py
exchangelib/__init__.py
exchangelib/account.py
exchangelib/attachments.py
exchangelib/autodiscover.py
exchangelib/configuration.py
exchangelib/credentials.py
exchangelib/errors.py
exchangelib/ewsdatetime.py
exchangelib/extended_properties.py
exchangelib/fields.py
exchangelib/folders.py
exchangelib/indexed_properties.py
exchangelib/items.py
exchangelib/properties.py
exchangelib/protocol.py
exchangelib/queryset.py
exchangelib/recurrence.py
exchangelib/restriction.py
exchangelib/services.py
exchangelib/settings.py
exchangelib/transport.py
exchangelib/util.py
exchangelib/version.py
exchangelib/winzone.py
exchangelibtmp.egg-info/PKG-INFO
exchangelibtmp.egg-info/SOURCES.txt
exchangelibtmp.egg-info/dependency_links.txt
exchangelibtmp.egg-info/not-zip-safe
exchangelibtmp.egg-info/requires.txt
exchangelibtmp.egg-info/top_level.txt