Metadata-Version: 2.1
Name: exchangelibtmp
Version: 1.12.2
Summary: Client for Microsoft Exchange Web Services (EWS)
Home-page: https://github.com/ecederstrand/exchangelib
Author: Erik Cederstrand
Author-email: erik@cederstrand.dk
License: BSD
Keywords: ews exchange autodiscover microsoft outlook exchange-web-services o365 office365
Platform: UNKNOWN
Classifier: Development Status :: 5 - Production/Stable
Classifier: Topic :: Communications
Classifier: License :: OSI Approved :: BSD License
Classifier: Programming Language :: Python :: 2
Classifier: Programming Language :: Python :: 3
Requires-Python: >=2.7, !=3.0.*, !=3.1.*, !=3.2.*, !=3.3.*
Provides-Extra: kerberos
